odoo/addons/odoo_filestore_s3/__init__.py
odoo/addons/odoo_filestore_s3/__manifest__.py
odoo/addons/odoo_filestore_s3/adapter.py
odoo/addons/odoo_filestore_s3/odoo_s3_fs.py
odoo/addons/odoo_filestore_s3/wrapt_patcher.py
mangono_odoo_s3_filestore-1.4.0.dist-info/METADATA
mangono_odoo_s3_filestore-1.4.0.dist-info/WHEEL
mangono_odoo_s3_filestore-1.4.0.dist-info/licenses/LICENSE
mangono_odoo_s3_filestore-1.4.0.dist-info/RECORD
