Metadata-Version: 2.4
Name: mangono-odoo-s3-filestore
Version: 1.4.0
Author-email: Alexis PASQUIER <alexis.pasquier@mangono.fr>
License-File: LICENSE
Classifier: Programming Language :: Python :: 3
Classifier: Programming Language :: Python :: 3 :: Only
Classifier: Programming Language :: Python :: 3.8
Classifier: Programming Language :: Python :: 3.9
Classifier: Programming Language :: Python :: 3.10
Classifier: Programming Language :: Python :: 3.11
Classifier: Programming Language :: Python :: 3.12
Requires-Python: >=3.8.19
Requires-Dist: minio>=7.2
Requires-Dist: oenv2config<2,>=1.5
Requires-Dist: oenv2config~=1.5
Requires-Dist: typing-extensions
Requires-Dist: wrapt<2,>=1.17.0
